quantumengine/__init__.py
quantumengine/aggregation.py
quantumengine/base_query.py
quantumengine/clickhouse_functions.py
quantumengine/connection_api.py
quantumengine/datagrid_api.py
quantumengine/document.py
quantumengine/exceptions.py
quantumengine/graph.py
quantumengine/logging.py
quantumengine/materialized_document.py
quantumengine/materialized_view.py
quantumengine/pagination.py
quantumengine/py.typed
quantumengine/query_expressions.py
quantumengine/query_expressions_pythonic.py
quantumengine/schema.py
quantumengine/schemaless.py
quantumengine/signals.py
quantumengine/types.py
quantumengine/backends/__init__.py
quantumengine/backends/base.py
quantumengine/backends/clickhouse.py
quantumengine/backends/redis.py
quantumengine/backends/surrealdb.py
quantumengine/backends/pools/__init__.py
quantumengine/backends/pools/clickhouse.py
quantumengine/backends/pools/redis.py
quantumengine/backends/pools/surrealdb.py
quantumengine/connection/__init__.py
quantumengine/connection/health.py
quantumengine/connection/manager.py
quantumengine/connection/pool.py
quantumengine/connection/stats.py
quantumengine/fields/__init__.py
quantumengine/fields/additional.py
quantumengine/fields/base.py
quantumengine/fields/clickhouse.py
quantumengine/fields/collection.py
quantumengine/fields/datetime.py
quantumengine/fields/geometry.py
quantumengine/fields/id.py
quantumengine/fields/reference.py
quantumengine/fields/scalar.py
quantumengine/fields/specialized.py
quantumengine/query/__init__.py
quantumengine/query/base.py
quantumengine/query/descriptor.py
quantumengine/query/relation.py
quantumengine-0.4.0.dist-info/licenses/LICENSE
quantumengine-0.4.0.dist-info/METADATA
quantumengine-0.4.0.dist-info/WHEEL
quantumengine-0.4.0.dist-info/top_level.txt
quantumengine-0.4.0.dist-info/RECORD
