Metadata-Version: 2.4
Name: quantumengine
Version: 0.4.0
Summary: Multi-Backend Object-Document Mapper (ODM) for ClickHouse, SurrealDB, and more - Quantum-Powered Database Engine
Author-email: Iristech Systems <contact@iristech.systems>
Maintainer-email: Iristech Systems <contact@iristech.systems>
License: MIT License
Project-URL: Homepage, https://github.com/iristech-systems/QuantumEngine
Project-URL: Repository, https://github.com/iristech-systems/QuantumEngine
Project-URL: Documentation, https://github.com/iristech-systems/QuantumEngine#readme
Project-URL: Bug Tracker, https://github.com/iristech-systems/QuantumEngine/issues
Project-URL: Changelog, https://github.com/iristech-systems/QuantumEngine/releases
Project-URL: Download, https://pypi.org/project/quantumengine/
Keywords: orm,odm,clickhouse,surrealdb,redis,dragonfly,database,async,multi-backend,analytics,graph-database,quantum,engine
Classifier: Development Status :: 4 - Beta
Classifier: Intended Audience :: Developers
Classifier: License :: OSI Approved :: MIT License
Classifier: Programming Language :: Python :: 3
Classifier: Programming Language :: Python :: 3.9
Classifier: Programming Language :: Python :: 3.10
Classifier: Programming Language :: Python :: 3.11
Classifier: Programming Language :: Python :: 3.12
Classifier: Topic :: Database
Classifier: Topic :: Database :: Database Engines/Servers
Classifier: Topic :: Software Development :: Libraries :: Python Modules
Classifier: Framework :: AsyncIO
Classifier: Operating System :: OS Independent
Classifier: Typing :: Typed
Requires-Python: >=3.9
License-File: LICENSE
Requires-Dist: typing-extensions>=4.0.0
Provides-Extra: clickhouse
Requires-Dist: clickhouse-connect>=0.7.0; extra == "clickhouse"
Provides-Extra: surrealdb
Requires-Dist: surrealdb==1.0.4; extra == "surrealdb"
Provides-Extra: redis
Requires-Dist: redis>=4.5.0; extra == "redis"
Provides-Extra: signals
Requires-Dist: blinker>=1.6.2; extra == "signals"
Provides-Extra: jupyter
Requires-Dist: notebook==7.2.2; extra == "jupyter"
Provides-Extra: dev
Requires-Dist: pytest>=7.0.0; extra == "dev"
Requires-Dist: pytest-asyncio>=0.20.0; extra == "dev"
Requires-Dist: mypy>=1.0.0; extra == "dev"
Requires-Dist: black>=22.0.0; extra == "dev"
Requires-Dist: ruff>=0.1.0; extra == "dev"
Provides-Extra: all
Requires-Dist: clickhouse-connect>=0.7.0; extra == "all"
Requires-Dist: surrealdb==1.0.4; extra == "all"
Requires-Dist: redis>=4.5.0; extra == "all"
Requires-Dist: blinker>=1.6.2; extra == "all"
Requires-Dist: notebook==7.2.2; extra == "all"
Dynamic: license-file
